funbgcex/BGCeXtractor.py
funbgcex/BGfinder.py
funbgcex/CoreAnnotation.py
funbgcex/GeneralCommands.py
funbgcex/HTMLgenerator.py
funbgcex/SeqHandling.py
funbgcex/SimilarBGCfinder.py
funbgcex/__init__.py
funbgcex/main.py
funbgcex/data/.DS_Store
funbgcex/data/Aspfum_proteins.csv
funbgcex/data/human_proteins.csv
funbgcex/data/proteins.csv
funbgcex/data/signal_peptide_model.keras
funbgcex/data/DIAMOND/AspfumDB.dmnd
funbgcex/data/DIAMOND/HumanDB.dmnd
funbgcex/data/DIAMOND/fungal_SM_proteins.dmnd
funbgcex/data/HTML/ALLtemplate.html
funbgcex/data/HTML/BGCtemplate.html
funbgcex/data/HTML/MAINtemplate.html
funbgcex/data/HTML/classification.html
funbgcex/data/HTML/hmm.csv
funbgcex/data/HTML/protfam.html
funbgcex/data/HTML/template.js
funbgcex/data/HTML/css/main_style.css
funbgcex/data/HTML/css/protfam_style.css
funbgcex/data/HTML/css/style.css
funbgcex/data/HTML/img/link.png
funbgcex/data/HTML/img/logo.png
funbgcex/data/HTML/js/filter.js
funbgcex/data/HTML/js/filter1.js
funbgcex/data/HTML/js/filter2.js
funbgcex/data/hmm/core/core.hmm
funbgcex/data/hmm/core/core.hmm.h3f
funbgcex/data/hmm/core/core.hmm.h3i
funbgcex/data/hmm/core/core.hmm.h3m
funbgcex/data/hmm/core/core.hmm.h3p
funbgcex/data/hmm/core/core_UstY.hmm
funbgcex/data/hmm/core/core_UstY.hmm.h3f
funbgcex/data/hmm/core/core_UstY.hmm.h3i
funbgcex/data/hmm/core/core_UstY.hmm.h3m
funbgcex/data/hmm/core/core_UstY.hmm.h3p
funbgcex/data/hmm/fungalSM/fungalSM.hmm
funbgcex/data/hmm/fungalSM/fungalSM.hmm.h3f
funbgcex/data/hmm/fungalSM/fungalSM.hmm.h3i
funbgcex/data/hmm/fungalSM/fungalSM.hmm.h3m
funbgcex/data/hmm/fungalSM/fungalSM.hmm.h3p
funbgcex/data/hmm/source/UstYa.hmm
funbgcex/data/hmm/source/core/AA-adenyl-dom.hmm
funbgcex/data/hmm/source/core/ABA3.hmm
funbgcex/data/hmm/source/core/ACP_PCP.hmm
funbgcex/data/hmm/source/core/Abhydrolase_3.hmm
funbgcex/data/hmm/source/core/Aminotran_5.hmm
funbgcex/data/hmm/source/core/AnkA.hmm
funbgcex/data/hmm/source/core/AsR6.hmm
funbgcex/data/hmm/source/core/AstC.hmm
funbgcex-1.0.0.dist-info/LICENSE
funbgcex-1.0.0.dist-info/METADATA
funbgcex-1.0.0.dist-info/WHEEL
funbgcex-1.0.0.dist-info/entry_points.txt
funbgcex-1.0.0.dist-info/top_level.txt
funbgcex-1.0.0.dist-info/RECORD
